JavaBianchengWentiChuyiFix1/README.md
JavaBianchengWentiChuyiFix1/__init__.py
JavaBianchengWentiChuyiFix1/__main__.py
JavaBianchengWentiChuyiFix1/file.epub
JavaBianchengWentiChuyiFix1/index.html
JavaBianchengWentiChuyiFix1/css/__init__.py
JavaBianchengWentiChuyiFix1/css/annotations.css
JavaBianchengWentiChuyiFix1/css/main.css
JavaBianchengWentiChuyiFix1/css/normalize.css
JavaBianchengWentiChuyiFix1/css/popup.css
JavaBianchengWentiChuyiFix1/font/__init__.py
JavaBianchengWentiChuyiFix1/font/fontello.eot
JavaBianchengWentiChuyiFix1/font/fontello.svg
JavaBianchengWentiChuyiFix1/font/fontello.ttf
JavaBianchengWentiChuyiFix1/font/fontello.woff
JavaBianchengWentiChuyiFix1/img/__init__.py
JavaBianchengWentiChuyiFix1/img/annotator-glyph-sprite.png
JavaBianchengWentiChuyiFix1/img/annotator-icon-sprite.png
JavaBianchengWentiChuyiFix1/img/apple-touch-icon.png
JavaBianchengWentiChuyiFix1/img/cancelfullscreen.png
JavaBianchengWentiChuyiFix1/img/close.png
JavaBianchengWentiChuyiFix1/img/fullscreen.png
JavaBianchengWentiChuyiFix1/img/loader.gif
JavaBianchengWentiChuyiFix1/img/menu-icon.png
JavaBianchengWentiChuyiFix1/img/save.png
JavaBianchengWentiChuyiFix1/img/saved.png
JavaBianchengWentiChuyiFix1/img/settings-s.png
JavaBianchengWentiChuyiFix1/img/settings.png
JavaBianchengWentiChuyiFix1/img/star.png
JavaBianchengWentiChuyiFix1/js/__init__.py
JavaBianchengWentiChuyiFix1/js/epub.js
JavaBianchengWentiChuyiFix1/js/epub.min.js
JavaBianchengWentiChuyiFix1/js/epub.min.map
JavaBianchengWentiChuyiFix1/js/hooks.min.js
JavaBianchengWentiChuyiFix1/js/hooks.min.map
JavaBianchengWentiChuyiFix1/js/reader.js
JavaBianchengWentiChuyiFix1/js/reader.js.map
JavaBianchengWentiChuyiFix1/js/reader.min.js
JavaBianchengWentiChuyiFix1/js/reader.min.map
JavaBianchengWentiChuyiFix1/js/hooks/__init__.py
JavaBianchengWentiChuyiFix1/js/hooks/extensions/__init__.py
JavaBianchengWentiChuyiFix1/js/hooks/extensions/highlight.js
JavaBianchengWentiChuyiFix1/js/libs/__init__.py
java_biancheng_wenti_chuyi_fix1-2025.3.25.0.dist-info/METADATA
java_biancheng_wenti_chuyi_fix1-2025.3.25.0.dist-info/WHEEL
java_biancheng_wenti_chuyi_fix1-2025.3.25.0.dist-info/entry_points.txt
java_biancheng_wenti_chuyi_fix1-2025.3.25.0.dist-info/top_level.txt
java_biancheng_wenti_chuyi_fix1-2025.3.25.0.dist-info/RECORD
